fedflow/ClientManager.py
fedflow/VagrantManager.py
fedflow/__init__.py
fedflow/cli.py
fedflow/config.py
fedflow/fcauto.py
fedflow/featurecloud_api.py
fedflow/logger.py
fedflow/provision.py
fedflow/utils.py
fedflow_featurecloud-0.0.1.dist-info/METADATA
fedflow_featurecloud-0.0.1.dist-info/WHEEL
fedflow_featurecloud-0.0.1.dist-info/entry_points.txt
fedflow_featurecloud-0.0.1.dist-info/licenses/LICENSE
fedflow_featurecloud-0.0.1.dist-info/RECORD
