Metadata-Version: 2.4
Name: fedflow-featurecloud
Version: 0.0.1
Summary: Federated FeatureCloud.ai workflows on remote machines
License-File: LICENSE
Requires-Python: >=3.10
Requires-Dist: fabric==3.2.2
Requires-Dist: featurecloud==0.1.0
Requires-Dist: httpx==0.28.1
Requires-Dist: pydantic==2.12.5
Requires-Dist: python-dotenv==1.2.1
Requires-Dist: tomli-w==1.2.0
